marleu_ec2/__init__.py
marleu_ec2/ec2.py
marleu_ec2-0.1.0.dist-info/entry_points.txt
marleu_ec2-0.1.0.dist-info/WHEEL
marleu_ec2-0.1.0.dist-info/METADATA
marleu_ec2-0.1.0.dist-info/RECORD
